[{"name": "XM1014", "family_name": "XOXO", "thumbnail": "https://steamcdn-a.akamaihd.net/apps/730/icons/econ/default_generated/weapon_xm1014_aq_xm1014_punk_light_large.8c6eb5bcf234179713a52b1a5e22c64c21c52007.png", "rarity": "classified", "type": "weapon", "exteriors": [{"exterior": "StatTrak Factory New", "price": 31.88, "coin": 318, "stattrak": true, "souvenir": false}, {"exterior": "StatTrak Minimal Wear", "price": 7.74, "coin": 77, "stattrak": true, "souvenir": false}, {"exterior": "StatTrak Field-Tested", "price": 3.58, "coin": 35, "stattrak": true, "souvenir": false}, {"exterior": "StatTrak Well-Worn", "price": 3.0, "coin": 30, "stattrak": true, "souvenir": false}, {"exterior": "StatTrak Battle-Scarred", "price": 2.47, "coin": 24, "stattrak": true, "souvenir": false}, {"exterior": "Factory New", "price": 9.06, "coin": 90, "stattrak": false, "souvenir": false}, {"exterior": "Minimal Wear", "price": 3.79, "coin": 37, "stattrak": false, "souvenir": false}, {"exterior": "Field-Tested", "price": 1.72, "coin": 17, "stattrak": false, "souvenir": false}, {"exterior": "Well-Worn", "price": 1.47, "coin": 14, "stattrak": false, "souvenir": false}, {"exterior": "Battle-Scarred", "price": 1.54, "coin": 15, "stattrak": false, "souvenir": false}]}, {"name": "XM1014", "family_name": "Entombed", "thumbnail": "https://steamcdn-a.akamaihd.net/apps/730/icons/econ/default_generated/weapon_xm1014_cu_xm1014_amulet_blue_light_large.1375467de64fba676253ac771bc9ce8f83b6a8f7.png", "rarity": "classified", "type": "weapon", "exteriors": [{"exterior": "StatTrak Factory New", "price": 19.76, "coin": 197, "stattrak": true, "souvenir": false}, {"exterior": "StatTrak Minimal Wear", "price": 8.99, "coin": 89, "stattrak": true, "souvenir": false}, {"exterior": "StatTrak Field-Tested", "price": 5.79, "coin": 57, "stattrak": true, "souvenir": false}, {"exterior": "StatTrak Well-Worn", "price": 3.74, "coin": 37, "stattrak": true, "souvenir": false}, {"exterior": "StatTrak Battle-Scarred", "price": 4.65, "coin": 46, "stattrak": true, "souvenir": false}, {"exterior": "Factory New", "price": 9.17, "coin": 91, "stattrak": false, "souvenir": false}, {"exterior": "Minimal Wear", "price": 5.85, "coin": 58, "stattrak": false, "souvenir": false}, {"exterior": "Field-Tested", "price": 3.5, "coin": 35, "stattrak": false, "souvenir": false}, {"exterior": "Well-Worn", "price": 2.98, "coin": 29, "stattrak": false, "souvenir": false}, {"exterior": "Battle-Scarred", "price": 3.02, "coin": 30, "stattrak": false, "souvenir": false}]}, {"name": "XM1014", "family_name": "Incinegator", "thumbnail": "https://steamcdn-a.akamaihd.net/apps/730/icons/econ/default_generated/weapon_xm1014_cu_xm1014_incinerator_light_large.7649f64bbfea49d6f0d951320e0bdd98d6bee088.png", "rarity": "classified", "type": "weapon", "exteriors": [{"exterior": "StatTrak Minimal Wear", "price": 60.03, "coin": 600, "stattrak": true, "souvenir": false}, {"exterior": "StatTrak Field-Tested", "price": 3.41, "coin": 34, "stattrak": true, "souvenir": false}, {"exterior": "StatTrak Well-Worn", "price": 7.52, "coin": 75, "stattrak": true, "souvenir": false}, {"exterior": "StatTrak Battle-Scarred", "price": 3.16, "coin": 31, "stattrak": true, "souvenir": false}, {"exterior": "Minimal Wear", "price": 15.12, "coin": 151, "stattrak": false, "souvenir": false}, {"exterior": "Field-Tested", "price": 1.92, "coin": 19, "stattrak": false, "souvenir": false}, {"exterior": "Well-Worn", "price": 1.98, "coin": 19, "stattrak": false, "souvenir": false}, {"exterior": "Battle-Scarred", "price": 1.34, "coin": 13, "stattrak": false, "souvenir": false}]}, {"name": "XM1014", "family_name": "Tranquility", "thumbnail": "https://steamcdn-a.akamaihd.net/apps/730/icons/econ/default_generated/weapon_xm1014_cu_xm1014_caritas_light_large.060e6378f5b5ab6fc53a2db451f3d68b8033f304.png", "rarity": "classified", "type": "weapon", "exteriors": [{"exterior": "StatTrak Factory New", "price": 114.64, "coin": 1146, "stattrak": true, "souvenir": false}, {"exterior": "StatTrak Minimal Wear", "price": 49.85, "coin": 498, "stattrak": true, "souvenir": false}, {"exterior": "StatTrak Field-Tested", "price": 20.55, "coin": 205, "stattrak": true, "souvenir": false}, {"exterior": "StatTrak Well-Worn", "price": 27.92, "coin": 279, "stattrak": true, "souvenir": false}, {"exterior": "StatTrak Battle-Scarred", "price": 18.39, "coin": 183, "stattrak": true, "souvenir": false}, {"exterior": "Factory New", "price": 23.93, "coin": 239, "stattrak": false, "souvenir": false}, {"exterior": "Minimal Wear", "price": 11.1, "coin": 111, "stattrak": false, "souvenir": false}, {"exterior": "Field-Tested", "price": 6.66, "coin": 66, "stattrak": false, "souvenir": false}, {"exterior": "Well-Worn", "price": 7.45, "coin": 74, "stattrak": false, "souvenir": false}, {"exterior": "Battle-Scarred", "price": 7.12, "coin": 71, "stattrak": false, "souvenir": false}]}, {"name": "XM1014", "family_name": "Zombie Offensive", "thumbnail": "https://steamcdn-a.akamaihd.net/apps/730/icons/econ/default_generated/weapon_xm1014_am_xm_zombie_offensive_light_large.0e15d69fbf9b3d93b14f54f85fa84bcb45c8f49e.png", "rarity": "restricted", "type": "weapon", "exteriors": [{"exterior": "StatTrak Factory New", "price": 2.86, "coin": 28, "stattrak": true, "souvenir": false}, {"exterior": "StatTrak Minimal Wear", "price": 1.15, "coin": 11, "stattrak": true, "souvenir": false}, {"exterior": "StatTrak Field-Tested", "price": 0.49, "coin": 4, "stattrak": true, "souvenir": false}, {"exterior": "StatTrak Well-Worn", "price": 0.48, "coin": 4, "stattrak": true, "souvenir": false}, {"exterior": "StatTrak Battle-Scarred", "price": 0.39, "coin": 3, "stattrak": true, "souvenir": false}, {"exterior": "Factory New", "price": 1.2, "coin": 12, "stattrak": false, "souvenir": false}, {"exterior": "Minimal Wear", "price": 0.55, "coin": 5, "stattrak": false, "souvenir": false}, {"exterior": "Field-Tested", "price": 0.31, "coin": 3, "stattrak": false, "souvenir": false}, {"exterior": "Well-Worn", "price": 0.3, "coin": 3, "stattrak": false, "souvenir": false}, {"exterior": "Battle-Scarred", "price": 0.29, "coin": 2, "stattrak": false, "souvenir": false}]}, {"name": "XM1014", "family_name": "Ziggy", "thumbnail": "https://steamcdn-a.akamaihd.net/apps/730/icons/econ/default_generated/weapon_xm1014_aq_xm1014_ziggy_anarchy_light_large.7042642ba5043be6e1cb82d6bb9a05678402dea1.png", "rarity": "restricted", "type": "weapon", "exteriors": [{"exterior": "StatTrak Factory New", "price": 3.43, "coin": 34, "stattrak": true, "souvenir": false}, {"exterior": "StatTrak Minimal Wear", "price": 2.08, "coin": 20, "stattrak": true, "souvenir": false}, {"exterior": "StatTrak Field-Tested", "price": 1.1, "coin": 11, "stattrak": true, "souvenir": false}, {"exterior": "StatTrak Well-Worn", "price": 1.9, "coin": 19, "stattrak": true, "souvenir": false}, {"exterior": "StatTrak Battle-Scarred", "price": 0.98, "coin": 9, "stattrak": true, "souvenir": false}, {"exterior": "Factory New", "price": 1.54, "coin": 15, "stattrak": false, "souvenir": false}, {"exterior": "Minimal Wear", "price": 0.8, "coin": 8, "stattrak": false, "souvenir": false}, {"exterior": "Field-Tested", "price": 0.39, "coin": 3, "stattrak": false, "souvenir": false}, {"exterior": "Well-Worn", "price": 0.46, "coin": 4, "stattrak": false, "souvenir": false}, {"exterior": "Battle-Scarred", "price": 0.34, "coin": 3, "stattrak": false, "souvenir": false}]}, {"name": "XM1014", "family_name": "Seasons", "thumbnail": "https://steamcdn-a.akamaihd.net/apps/730/icons/econ/default_generated/weapon_xm1014_aq_xm_leaf_fade_light_large.f753b1b710a8023e299d1918ca150b42483ca1cd.png", "rarity": "restricted", "type": "weapon", "exteriors": [{"exterior": "StatTrak Factory New", "price": 6.58, "coin": 65, "stattrak": true, "souvenir": false}, {"exterior": "StatTrak Minimal Wear", "price": 3.7, "coin": 37, "stattrak": true, "souvenir": false}, {"exterior": "StatTrak Field-Tested", "price": 2.91, "coin": 29, "stattrak": true, "souvenir": false}, {"exterior": "StatTrak Well-Worn", "price": 3.55, "coin": 35, "stattrak": true, "souvenir": false}, {"exterior": "StatTrak Battle-Scarred", "price": 2.98, "coin": 29, "stattrak": true, "souvenir": false}, {"exterior": "Factory New", "price": 3.6, "coin": 36, "stattrak": false, "souvenir": false}, {"exterior": "Minimal Wear", "price": 2.13, "coin": 21, "stattrak": false, "souvenir": false}, {"exterior": "Field-Tested", "price": 1.56, "coin": 15, "stattrak": false, "souvenir": false}, {"exterior": "Well-Worn", "price": 1.5, "coin": 15, "stattrak": false, "souvenir": false}, {"exterior": "Battle-Scarred", "price": 1.59, "coin": 15, "stattrak": false, "souvenir": false}]}, {"name": "XM1014", "family_name": "Black Tie", "thumbnail": "https://steamcdn-a.akamaihd.net/apps/730/icons/econ/default_generated/weapon_xm1014_cu_xm1014_spectrum_light_large.6318ee51c405fb5e8a40aedfc3d98d530f789a5b.png", "rarity": "restricted", "type": "weapon", "exteriors": [{"exterior": "StatTrak Factory New", "price": 14.23, "coin": 142, "stattrak": true, "souvenir": false}, {"exterior": "StatTrak Minimal Wear", "price": 3.89, "coin": 38, "stattrak": true, "souvenir": false}, {"exterior": "StatTrak Field-Tested", "price": 1.06, "coin": 10, "stattrak": true, "souvenir": false}, {"exterior": "StatTrak Well-Worn", "price": 1.4, "coin": 14, "stattrak": true, "souvenir": false}, {"exterior": "StatTrak Battle-Scarred", "price": 9971.59, "coin": 99715, "stattrak": true, "souvenir": false}, {"exterior": "Factory New", "price": 2.56, "coin": 25, "stattrak": false, "souvenir": false}, {"exterior": "Minimal Wear", "price": 0.97, "coin": 9, "stattrak": false, "souvenir": false}, {"exterior": "Field-Tested", "price": 0.39, "coin": 3, "stattrak": false, "souvenir": false}, {"exterior": "Well-Worn", "price": 0.39, "coin": 3, "stattrak": false, "souvenir": false}, {"exterior": "Battle-Scarred", "price": 0.32, "coin": 3, "stattrak": false, "souvenir": false}]}, {"name": "XM1014", "family_name": "Teclu Burner", "thumbnail": "https://steamcdn-a.akamaihd.net/apps/730/icons/econ/default_generated/weapon_xm1014_aq_xm1014_hot_rod_light_large.f664b036e9b4ec638574f17a9b7ea0905e8c57e0.png", "rarity": "restricted", "type": "weapon", "exteriors": [{"exterior": "StatTrak Factory New", "price": 8.03, "coin": 80, "stattrak": true, "souvenir": false}, {"exterior": "StatTrak Minimal Wear", "price": 4.77, "coin": 47, "stattrak": true, "souvenir": false}, {"exterior": "StatTrak Field-Tested", "price": 2.14, "coin": 21, "stattrak": true, "souvenir": false}, {"exterior": "StatTrak Well-Worn", "price": 2.88, "coin": 28, "stattrak": true, "souvenir": false}, {"exterior": "StatTrak Battle-Scarred", "price": 2.3, "coin": 23, "stattrak": true, "souvenir": false}, {"exterior": "Factory New", "price": 2.78, "coin": 27, "stattrak": false, "souvenir": false}, {"exterior": "Minimal Wear", "price": 1.34, "coin": 13, "stattrak": false, "souvenir": false}, {"exterior": "Field-Tested", "price": 0.71, "coin": 7, "stattrak": false, "souvenir": false}, {"exterior": "Well-Worn", "price": 1.0, "coin": 10, "stattrak": false, "souvenir": false}, {"exterior": "Battle-Scarred", "price": 0.72, "coin": 7, "stattrak": false, "souvenir": false}]}, {"name": "XM1014", "family_name": "Heaven Guard", "thumbnail": "https://steamcdn-a.akamaihd.net/apps/730/icons/econ/default_generated/weapon_xm1014_cu_xm1014_heaven_guard_light_large.c7f3f8815f9caa92daa5ffe4390880c1606f4a81.png", "rarity": "restricted", "type": "weapon", "exteriors": [{"exterior": "StatTrak Factory New", "price": 29.65, "coin": 296, "stattrak": true, "souvenir": false}, {"exterior": "StatTrak Minimal Wear", "price": 17.68, "coin": 176, "stattrak": true, "souvenir": false}, {"exterior": "StatTrak Field-Tested", "price": 13.88, "coin": 138, "stattrak": true, "souvenir": false}, {"exterior": "StatTrak Well-Worn", "price": 12.81, "coin": 128, "stattrak": true, "souvenir": false}, {"exterior": "StatTrak Battle-Scarred", "price": 13.78, "coin": 137, "stattrak": true, "souvenir": false}, {"exterior": "Factory New", "price": 24.93, "coin": 249, "stattrak": false, "souvenir": false}, {"exterior": "Minimal Wear", "price": 10.36, "coin": 103, "stattrak": false, "souvenir": false}, {"exterior": "Field-Tested", "price": 9.08, "coin": 90, "stattrak": false, "souvenir": false}, {"exterior": "Well-Worn", "price": 7.45, "coin": 74, "stattrak": false, "souvenir": false}, {"exterior": "Battle-Scarred", "price": 7.97, "coin": 79, "stattrak": false, "souvenir": false}]}, {"name": "XM1014", "family_name": "Elegant Vines", "thumbnail": "https://steamcdn-a.akamaihd.net/apps/730/icons/econ/default_generated/weapon_xm1014_am_moro_textile_bright_light_large.90d9c102cff5e50e56b5d4bdc9c967ab7ae7efd8.png", "rarity": "restricted", "type": "weapon", "exteriors": [{"exterior": "Factory New", "price": 84.41, "coin": 844, "stattrak": false, "souvenir": false}, {"exterior": "Minimal Wear", "price": 74.24, "coin": 742, "stattrak": false, "souvenir": false}, {"exterior": "Field-Tested", "price": 77.41, "coin": 774, "stattrak": false, "souvenir": false}, {"exterior": "Souvenir Factory New", "price": 2.72, "coin": 27, "stattrak": false, "souvenir": true}, {"exterior": "Souvenir Minimal Wear", "price": 1.17, "coin": 11, "stattrak": false, "souvenir": true}, {"exterior": "Souvenir Field-Tested", "price": 0.94, "coin": 9, "stattrak": false, "souvenir": true}]}, {"name": "XM1014", "family_name": "Ancient Lore", "thumbnail": "https://steamcdn-a.akamaihd.net/apps/730/icons/econ/default_generated/weapon_xm1014_am_ancient_warm_light_large.9a53c1b2db897b005c56b8f5e4a5b9f40730c85b.png", "rarity": "restricted", "type": "weapon", "exteriors": [{"exterior": "Factory New", "price": 57.19, "coin": 571, "stattrak": false, "souvenir": false}, {"exterior": "Minimal Wear", "price": 38.89, "coin": 388, "stattrak": false, "souvenir": false}, {"exterior": "Field-Tested", "price": 51.24, "coin": 512, "stattrak": false, "souvenir": false}, {"exterior": "Well-Worn", "price": 74.28, "coin": 742, "stattrak": false, "souvenir": false}, {"exterior": "Battle-Scarred", "price": 63.89, "coin": 638, "stattrak": false, "souvenir": false}, {"exterior": "Souvenir Factory New", "price": 3.12, "coin": 31, "stattrak": false, "souvenir": true}, {"exterior": "Souvenir Minimal Wear", "price": 2.45, "coin": 24, "stattrak": false, "souvenir": true}, {"exterior": "Souvenir Field-Tested", "price": 1.54, "coin": 15, "stattrak": false, "souvenir": true}, {"exterior": "Souvenir Well-Worn", "price": 2.26, "coin": 22, "stattrak": false, "souvenir": true}, {"exterior": "Souvenir Battle-Scarred", "price": 6.97, "coin": 69, "stattrak": false, "souvenir": true}]}, {"name": "XM1014", "family_name": "Irezumi", "thumbnail": "https://steamcommunity-a.akamaihd.net/economy/image/-9a81dlWLwJ2UUGcVs_nsVtzdOEdtWwKGZZLQHTxDZ7I56KU0Zwwo4NUX4oFJZEHLbXH5ApeO4YmlhxYQknCRvCo04DEVlxkKgporrf0e1Y07OvFIG0TuOO_hoWRgvr9DLfYkWNFpsMk2LjH8dis2Abg8xA4YDr7ctWVdAM5ZFHY-1K8xrzn1sTv6szPyCN9-n51nuU3Vic/512fx384f", "rarity": "mil-spec", "type": "weapon", "exteriors": [{"exterior": "StatTrak Factory New", "price": 1.46, "coin": 14, "stattrak": true, "souvenir": false}, {"exterior": "StatTrak Minimal Wear", "price": 0.97, "coin": 9, "stattrak": true, "souvenir": false}, {"exterior": "StatTrak Field-Tested", "price": 0.29, "coin": 2, "stattrak": true, "souvenir": false}, {"exterior": "StatTrak Well-Worn", "price": 1.24, "coin": 12, "stattrak": true, "souvenir": false}, {"exterior": "StatTrak Battle-Scarred", "price": 0.24, "coin": 2, "stattrak": true, "souvenir": false}, {"exterior": "Factory New", "price": 0.35, "coin": 3, "stattrak": false, "souvenir": false}, {"exterior": "Minimal Wear", "price": 0.28, "coin": 2, "stattrak": false, "souvenir": false}, {"exterior": "Field-Tested", "price": 0.33, "coin": 3, "stattrak": false, "souvenir": false}, {"exterior": "Well-Worn", "price": 0.25, "coin": 2, "stattrak": false, "souvenir": false}, {"exterior": "Battle-Scarred", "price": 0.17, "coin": 1, "stattrak": false, "souvenir": false}]}, {"name": "XM1014", "family_name": "Watchdog", "thumbnail": "https://steamcdn-a.akamaihd.net/apps/730/icons/econ/default_generated/weapon_xm1014_gs_xm1014_watchdog_light_large.5443196414c00a57b26d9af50d4a75a35dd8dbd8.png", "rarity": "mil-spec", "type": "weapon", "exteriors": [{"exterior": "StatTrak Factory New", "price": 24.55, "coin": 245, "stattrak": true, "souvenir": false}, {"exterior": "StatTrak Minimal Wear", "price": 5.51, "coin": 55, "stattrak": true, "souvenir": false}, {"exterior": "StatTrak Field-Tested", "price": 2.53, "coin": 25, "stattrak": true, "souvenir": false}, {"exterior": "StatTrak Well-Worn", "price": 1.5, "coin": 15, "stattrak": true, "souvenir": false}, {"exterior": "StatTrak Battle-Scarred", "price": 2.85, "coin": 28, "stattrak": true, "souvenir": false}, {"exterior": "Factory New", "price": 5.54, "coin": 55, "stattrak": false, "souvenir": false}, {"exterior": "Minimal Wear", "price": 1.82, "coin": 18, "stattrak": false, "souvenir": false}, {"exterior": "Field-Tested", "price": 1.17, "coin": 11, "stattrak": false, "souvenir": false}, {"exterior": "Well-Worn", "price": 0.74, "coin": 7, "stattrak": false, "souvenir": false}, {"exterior": "Battle-Scarred", "price": 1.0, "coin": 10, "stattrak": false, "souvenir": false}]}, {"name": "XM1014", "family_name": "Oxide Blaze", "thumbnail": "https://steamcdn-a.akamaihd.net/apps/730/icons/econ/default_generated/weapon_xm1014_cu_xm1014_oxide_blaze_light_large.691be80b706e1ea4faf9b5c9bec40b3611b1d440.png", "rarity": "mil-spec", "type": "weapon", "exteriors": [{"exterior": "StatTrak Factory New", "price": 0.78, "coin": 7, "stattrak": true, "souvenir": false}, {"exterior": "StatTrak Minimal Wear", "price": 0.3, "coin": 3, "stattrak": true, "souvenir": false}, {"exterior": "StatTrak Field-Tested", "price": 0.11, "coin": 1, "stattrak": true, "souvenir": false}, {"exterior": "StatTrak Well-Worn", "price": 0.21, "coin": 2, "stattrak": true, "souvenir": false}, {"exterior": "StatTrak Battle-Scarred", "price": 0.11, "coin": 1, "stattrak": true, "souvenir": false}, {"exterior": "Factory New", "price": 0.21, "coin": 2, "stattrak": false, "souvenir": false}, {"exterior": "Minimal Wear", "price": 0.1, "coin": 1, "stattrak": false, "souvenir": false}, {"exterior": "Field-Tested", "price": 0.06, "coin": 1, "stattrak": false, "souvenir": false}, {"exterior": "Well-Worn", "price": 0.03, "coin": 1, "stattrak": false, "souvenir": false}, {"exterior": "Battle-Scarred", "price": 0.05, "coin": 1, "stattrak": false, "souvenir": false}]}, {"name": "XM1014", "family_name": "Slipstream", "thumbnail": "https://steamcdn-a.akamaihd.net/apps/730/icons/econ/default_generated/weapon_xm1014_hy_xm1014_fractal_blue_light_large.e9720fb7b5928db8bcf79d62850af5bf475b9ec5.png", "rarity": "mil-spec", "type": "weapon", "exteriors": [{"exterior": "StatTrak Factory New", "price": 1.43, "coin": 14, "stattrak": true, "souvenir": false}, {"exterior": "StatTrak Minimal Wear", "price": 0.81, "coin": 8, "stattrak": true, "souvenir": false}, {"exterior": "StatTrak Field-Tested", "price": 0.29, "coin": 2, "stattrak": true, "souvenir": false}, {"exterior": "StatTrak Well-Worn", "price": 0.47, "coin": 4, "stattrak": true, "souvenir": false}, {"exterior": "StatTrak Battle-Scarred", "price": 0.3, "coin": 3, "stattrak": true, "souvenir": false}, {"exterior": "Factory New", "price": 0.38, "coin": 3, "stattrak": false, "souvenir": false}, {"exterior": "Minimal Wear", "price": 0.2, "coin": 2, "stattrak": false, "souvenir": false}, {"exterior": "Field-Tested", "price": 0.09, "coin": 1, "stattrak": false, "souvenir": false}, {"exterior": "Well-Worn", "price": 0.09, "coin": 1, "stattrak": false, "souvenir": false}, {"exterior": "Battle-Scarred", "price": 0.08, "coin": 1, "stattrak": false, "souvenir": false}]}, {"name": "XM1014", "family_name": "Scumbria", "thumbnail": "https://steamcdn-a.akamaihd.net/apps/730/icons/econ/default_generated/weapon_xm1014_aq_xm1014_scumbria_light_large.b8e79b3c4391784151d789edde360dbaaef7fd1f.png", "rarity": "mil-spec", "type": "weapon", "exteriors": [{"exterior": "StatTrak Factory New", "price": 3.69, "coin": 36, "stattrak": true, "souvenir": false}, {"exterior": "StatTrak Minimal Wear", "price": 0.93, "coin": 9, "stattrak": true, "souvenir": false}, {"exterior": "StatTrak Field-Tested", "price": 0.39, "coin": 3, "stattrak": true, "souvenir": false}, {"exterior": "StatTrak Well-Worn", "price": 0.36, "coin": 3, "stattrak": true, "souvenir": false}, {"exterior": "StatTrak Battle-Scarred", "price": 0.31, "coin": 3, "stattrak": true, "souvenir": false}, {"exterior": "Factory New", "price": 1.4, "coin": 14, "stattrak": false, "souvenir": false}, {"exterior": "Minimal Wear", "price": 0.34, "coin": 3, "stattrak": false, "souvenir": false}, {"exterior": "Field-Tested", "price": 0.17, "coin": 1, "stattrak": false, "souvenir": false}, {"exterior": "Well-Worn", "price": 0.16, "coin": 1, "stattrak": false, "souvenir": false}, {"exterior": "Battle-Scarred", "price": 0.15, "coin": 1, "stattrak": false, "souvenir": false}]}, {"name": "XM1014", "family_name": "Quicksilver", "thumbnail": "https://steamcdn-a.akamaihd.net/apps/730/icons/econ/default_generated/weapon_xm1014_aq_xm1014_sigla_light_large.71c180cd3b8bdea7d0b119ab2b9d54792c51b3aa.png", "rarity": "mil-spec", "type": "weapon", "exteriors": [{"exterior": "StatTrak Factory New", "price": 1.63, "coin": 16, "stattrak": true, "souvenir": false}, {"exterior": "StatTrak Minimal Wear", "price": 1.15, "coin": 11, "stattrak": true, "souvenir": false}, {"exterior": "StatTrak Field-Tested", "price": 0.61, "coin": 6, "stattrak": true, "souvenir": false}, {"exterior": "StatTrak Well-Worn", "price": 1.22, "coin": 12, "stattrak": true, "souvenir": false}, {"exterior": "StatTrak Battle-Scarred", "price": 0.89, "coin": 8, "stattrak": true, "souvenir": false}, {"exterior": "Factory New", "price": 0.47, "coin": 4, "stattrak": false, "souvenir": false}, {"exterior": "Minimal Wear", "price": 0.34, "coin": 3, "stattrak": false, "souvenir": false}, {"exterior": "Field-Tested", "price": 0.23, "coin": 2, "stattrak": false, "souvenir": false}, {"exterior": "Well-Worn", "price": 0.37, "coin": 3, "stattrak": false, "souvenir": false}, {"exterior": "Battle-Scarred", "price": 0.36, "coin": 3, "stattrak": false, "souvenir": false}]}, {"name": "XM1014", "family_name": "Red Python", "thumbnail": "https://steamcdn-a.akamaihd.net/apps/730/icons/econ/default_generated/weapon_xm1014_hy_snakeskin_red_light_large.d019a25e10fe53f2edf2958fb322c59621abc4de.png", "rarity": "mil-spec", "type": "weapon", "exteriors": [{"exterior": "StatTrak Minimal Wear", "price": 3.93, "coin": 39, "stattrak": true, "souvenir": false}, {"exterior": "StatTrak Field-Tested", "price": 2.09, "coin": 20, "stattrak": true, "souvenir": false}, {"exterior": "StatTrak Well-Worn", "price": 2.26, "coin": 22, "stattrak": true, "souvenir": false}, {"exterior": "StatTrak Battle-Scarred", "price": 2.72, "coin": 27, "stattrak": true, "souvenir": false}, {"exterior": "Minimal Wear", "price": 2.62, "coin": 26, "stattrak": false, "souvenir": false}, {"exterior": "Field-Tested", "price": 2.44, "coin": 24, "stattrak": false, "souvenir": false}, {"exterior": "Well-Worn", "price": 2.45, "coin": 24, "stattrak": false, "souvenir": false}, {"exterior": "Battle-Scarred", "price": 3.3, "coin": 33, "stattrak": false, "souvenir": false}]}, {"name": "XM1014", "family_name": "Frost Borre", "thumbnail": "https://steamcdn-a.akamaihd.net/apps/730/icons/econ/default_generated/weapon_xm1014_am_knots_silver_light_large.73c743e4867ffc0525bc79c488dc90cc12ee53ac.png", "rarity": "mil-spec", "type": "weapon", "exteriors": [{"exterior": "Factory New", "price": 199.45, "coin": 1994, "stattrak": false, "souvenir": false}, {"exterior": "Minimal Wear", "price": 1867.65, "coin": 18676, "stattrak": false, "souvenir": false}, {"exterior": "Field-Tested", "price": 114.68, "coin": 1146, "stattrak": false, "souvenir": false}, {"exterior": "Well-Worn", "price": 159.91, "coin": 1599, "stattrak": false, "souvenir": false}, {"exterior": "Battle-Scarred", "price": 798.0, "coin": 7980, "stattrak": false, "souvenir": false}]}, {"name": "XM1014", "family_name": "Bone Machine", "thumbnail": "https://steamcdn-a.akamaihd.net/apps/730/icons/econ/default_generated/weapon_xm1014_am_nuclear_skulls1_xm1014_light_large.716e8296c07d3e6d5c9f5f20605c9608bbb78ca1.png", "rarity": "mil-spec", "type": "weapon", "exteriors": [{"exterior": "Factory New", "price": 9.98, "coin": 99, "stattrak": false, "souvenir": false}, {"exterior": "Minimal Wear", "price": 7.45, "coin": 74, "stattrak": false, "souvenir": false}, {"exterior": "Field-Tested", "price": 6.32, "coin": 63, "stattrak": false, "souvenir": false}, {"exterior": "Well-Worn", "price": 5.58, "coin": 55, "stattrak": false, "souvenir": false}, {"exterior": "Battle-Scarred", "price": 5.09, "coin": 50, "stattrak": false, "souvenir": false}, {"exterior": "Souvenir Factory New", "price": 30.91, "coin": 309, "stattrak": false, "souvenir": true}, {"exterior": "Souvenir Minimal Wear", "price": 19.94, "coin": 199, "stattrak": false, "souvenir": true}, {"exterior": "Souvenir Field-Tested", "price": 5.77, "coin": 57, "stattrak": false, "souvenir": true}, {"exterior": "Souvenir Well-Worn", "price": 7.28, "coin": 72, "stattrak": false, "souvenir": true}, {"exterior": "Souvenir Battle-Scarred", "price": 7.15, "coin": 71, "stattrak": false, "souvenir": true}]}, {"name": "XM1014", "family_name": "Red Leather", "thumbnail": "https://steamcdn-a.akamaihd.net/apps/730/icons/econ/default_generated/weapon_xm1014_cu_leather_xm1014_light_large.4b2f6f7df7d03f0bfb271d1d06c948bb8cdcb0c0.png", "rarity": "mil-spec", "type": "weapon", "exteriors": [{"exterior": "Factory New", "price": 58.22, "coin": 582, "stattrak": false, "souvenir": false}, {"exterior": "Minimal Wear", "price": 234.16, "coin": 2341, "stattrak": false, "souvenir": false}, {"exterior": "Field-Tested", "price": 9971.59, "coin": 99715, "stattrak": false, "souvenir": false}, {"exterior": "Well-Worn", "price": 58.73, "coin": 587, "stattrak": false, "souvenir": false}, {"exterior": "Battle-Scarred", "price": 91.3, "coin": 913, "stattrak": false, "souvenir": false}]}, {"name": "XM1014", "family_name": "VariCamo Blue", "thumbnail": "https://steamcdn-a.akamaihd.net/apps/730/icons/econ/default_generated/weapon_xm1014_hy_varicamo_blue_light_large.6b99e2f4d5092295c86b872e2a08d7ea698fe5b6.png", "rarity": "mil-spec", "type": "weapon", "exteriors": [{"exterior": "Factory New", "price": 26.33, "coin": 263, "stattrak": false, "souvenir": false}, {"exterior": "Minimal Wear", "price": 26.44, "coin": 264, "stattrak": false, "souvenir": false}, {"exterior": "Field-Tested", "price": 18.95, "coin": 189, "stattrak": false, "souvenir": false}, {"exterior": "Well-Worn", "price": 37.9, "coin": 379, "stattrak": false, "souvenir": false}, {"exterior": "Battle-Scarred", "price": 17.2, "coin": 172, "stattrak": false, "souvenir": false}, {"exterior": "Souvenir Factory New", "price": 3.34, "coin": 33, "stattrak": false, "souvenir": true}, {"exterior": "Souvenir Minimal Wear", "price": 2.03, "coin": 20, "stattrak": false, "souvenir": true}, {"exterior": "Souvenir Field-Tested", "price": 0.62, "coin": 6, "stattrak": false, "souvenir": true}, {"exterior": "Souvenir Well-Worn", "price": 1.99, "coin": 19, "stattrak": false, "souvenir": true}, {"exterior": "Souvenir Battle-Scarred", "price": 1.5, "coin": 15, "stattrak": false, "souvenir": true}]}, {"name": "XM1014", "family_name": "Blaze Orange", "thumbnail": "https://steamcdn-a.akamaihd.net/apps/730/icons/econ/default_generated/weapon_xm1014_hy_hunter_blaze_orange_light_large.def31710e14b573829a2138ffc7c3eadb3f49e5c.png", "rarity": "mil-spec", "type": "weapon", "exteriors": [{"exterior": "Factory New", "price": 373.66, "coin": 3736, "stattrak": false, "souvenir": false}, {"exterior": "Minimal Wear", "price": 184.14, "coin": 1841, "stattrak": false, "souvenir": false}, {"exterior": "Field-Tested", "price": 12.96, "coin": 129, "stattrak": false, "souvenir": false}, {"exterior": "Well-Worn", "price": 19.43, "coin": 194, "stattrak": false, "souvenir": false}, {"exterior": "Battle-Scarred", "price": 17.2, "coin": 172, "stattrak": false, "souvenir": false}]}, {"name": "XM1014", "family_name": "Banana Leaf", "thumbnail": "https://steamcdn-a.akamaihd.net/apps/730/icons/econ/default_generated/weapon_xm1014_hy_leaf_green_light_large.347a54ae0c8292ff6dc506dcf1702de2040a7459.png", "rarity": "industrial", "type": "weapon", "exteriors": [{"exterior": "Factory New", "price": 29.22, "coin": 292, "stattrak": false, "souvenir": false}, {"exterior": "Minimal Wear", "price": 26.2, "coin": 262, "stattrak": false, "souvenir": false}, {"exterior": "Field-Tested", "price": 24.55, "coin": 245, "stattrak": false, "souvenir": false}, {"exterior": "Well-Worn", "price": 24.43, "coin": 244, "stattrak": false, "souvenir": false}, {"exterior": "Battle-Scarred", "price": 28.38, "coin": 283, "stattrak": false, "souvenir": false}]}, {"name": "XM1014", "family_name": "Blue Steel", "thumbnail": "https://steamcdn-a.akamaihd.net/apps/730/icons/econ/default_generated/weapon_xm1014_aq_blued_light_large.322850eb06df5352f302b6d4dffb1d2472dac596.png", "rarity": "industrial", "type": "weapon", "exteriors": [{"exterior": "Factory New", "price": 0.35, "coin": 3, "stattrak": false, "souvenir": false}, {"exterior": "Minimal Wear", "price": 0.03, "coin": 1, "stattrak": false, "souvenir": false}, {"exterior": "Field-Tested", "price": 0.02, "coin": 1, "stattrak": false, "souvenir": false}, {"exterior": "Well-Worn", "price": 0.03, "coin": 1, "stattrak": false, "souvenir": false}, {"exterior": "Battle-Scarred", "price": 0.02, "coin": 1, "stattrak": false, "souvenir": false}, {"exterior": "Souvenir Factory New", "price": 0.0, "coin": 1, "stattrak": false, "souvenir": true}, {"exterior": "Souvenir Minimal Wear", "price": 81.43, "coin": 814, "stattrak": false, "souvenir": true}, {"exterior": "Souvenir Field-Tested", "price": 83.66, "coin": 836, "stattrak": false, "souvenir": true}, {"exterior": "Souvenir Well-Worn", "price": 54.06, "coin": 540, "stattrak": false, "souvenir": true}, {"exterior": "Souvenir Battle-Scarred", "price": 442.54, "coin": 4425, "stattrak": false, "souvenir": true}]}, {"name": "XM1014", "family_name": "CaliCamo", "thumbnail": "https://steamcdn-a.akamaihd.net/apps/730/icons/econ/default_generated/weapon_xm1014_hy_varicamo_desert_light_large.8931cbff2aa329928977420d05616b306eb0a91f.png", "rarity": "industrial", "type": "weapon", "exteriors": [{"exterior": "Factory New", "price": 0.08, "coin": 1, "stattrak": false, "souvenir": false}, {"exterior": "Minimal Wear", "price": 0.03, "coin": 1, "stattrak": false, "souvenir": false}, {"exterior": "Field-Tested", "price": 0.02, "coin": 1, "stattrak": false, "souvenir": false}, {"exterior": "Well-Worn", "price": 0.03, "coin": 1, "stattrak": false, "souvenir": false}, {"exterior": "Battle-Scarred", "price": 0.02, "coin": 1, "stattrak": false, "souvenir": false}, {"exterior": "Souvenir Factory New", "price": 112.47, "coin": 1124, "stattrak": false, "souvenir": true}, {"exterior": "Souvenir Minimal Wear", "price": 31.61, "coin": 316, "stattrak": false, "souvenir": true}, {"exterior": "Souvenir Field-Tested", "price": 321.02, "coin": 3210, "stattrak": false, "souvenir": true}, {"exterior": "Souvenir Well-Worn", "price": 0.0, "coin": 1, "stattrak": false, "souvenir": true}, {"exterior": "Souvenir Battle-Scarred", "price": 0.0, "coin": 1, "stattrak": false, "souvenir": true}]}, {"name": "XM1014", "family_name": "Fallout Warning", "thumbnail": "https://steamcdn-a.akamaihd.net/apps/730/icons/econ/default_generated/weapon_xm1014_sp_nukestripe_maroon_light_large.8b6facf30ed6057509fcaf2c8a75a04c2629203a.png", "rarity": "industrial", "type": "weapon", "exteriors": [{"exterior": "Factory New", "price": 203.17, "coin": 2031, "stattrak": false, "souvenir": false}, {"exterior": "Minimal Wear", "price": 24.92, "coin": 249, "stattrak": false, "souvenir": false}, {"exterior": "Field-Tested", "price": 8.97, "coin": 89, "stattrak": false, "souvenir": false}, {"exterior": "Well-Worn", "price": 8.16, "coin": 81, "stattrak": false, "souvenir": false}, {"exterior": "Battle-Scarred", "price": 8.04, "coin": 80, "stattrak": false, "souvenir": false}, {"exterior": "Souvenir Factory New", "price": 746.21, "coin": 7462, "stattrak": false, "souvenir": true}, {"exterior": "Souvenir Minimal Wear", "price": 18.03, "coin": 180, "stattrak": false, "souvenir": true}, {"exterior": "Souvenir Field-Tested", "price": 3.78, "coin": 37, "stattrak": false, "souvenir": true}, {"exterior": "Souvenir Well-Worn", "price": 21.94, "coin": 219, "stattrak": false, "souvenir": true}, {"exterior": "Souvenir Battle-Scarred", "price": 3.52, "coin": 35, "stattrak": false, "souvenir": true}]}, {"name": "XM1014", "family_name": "Hieroglyph", "thumbnail": "https://steamcdn-a.akamaihd.net/apps/730/icons/econ/default_generated/weapon_xm1014_cu_xm1014_pharaoh_light_large.dd51bfb65f740dd4145fb548ef9be0a353f82766.png", "rarity": "consumer", "type": "weapon", "exteriors": [{"exterior": "Factory New", "price": 0.18, "coin": 1, "stattrak": false, "souvenir": false}, {"exterior": "Minimal Wear", "price": 0.02, "coin": 1, "stattrak": false, "souvenir": false}, {"exterior": "Field-Tested", "price": 0.01, "coin": 1, "stattrak": false, "souvenir": false}, {"exterior": "Well-Worn", "price": 0.03, "coin": 1, "stattrak": false, "souvenir": false}, {"exterior": "Battle-Scarred", "price": 0.03, "coin": 1, "stattrak": false, "souvenir": false}, {"exterior": "Souvenir Factory New", "price": 0.62, "coin": 6, "stattrak": false, "souvenir": true}, {"exterior": "Souvenir Minimal Wear", "price": 0.03, "coin": 1, "stattrak": false, "souvenir": true}, {"exterior": "Souvenir Field-Tested", "price": 0.01, "coin": 1, "stattrak": false, "souvenir": true}, {"exterior": "Souvenir Well-Worn", "price": 0.01, "coin": 1, "stattrak": false, "souvenir": true}, {"exterior": "Souvenir Battle-Scarred", "price": 0.25, "coin": 2, "stattrak": false, "souvenir": true}]}, {"name": "XM1014", "family_name": "Blue Tire", "thumbnail": "https://steamcdn-a.akamaihd.net/apps/730/icons/econ/default_generated/weapon_xm1014_sp_tire_tread_blue_light_large.c6107f07580de4c0d1440aacabbd8b47b788a687.png", "rarity": "consumer", "type": "weapon", "exteriors": [{"exterior": "Factory New", "price": 1.41, "coin": 14, "stattrak": false, "souvenir": false}, {"exterior": "Minimal Wear", "price": 0.89, "coin": 8, "stattrak": false, "souvenir": false}, {"exterior": "Field-Tested", "price": 0.98, "coin": 9, "stattrak": false, "souvenir": false}, {"exterior": "Well-Worn", "price": 0.97, "coin": 9, "stattrak": false, "souvenir": false}, {"exterior": "Battle-Scarred", "price": 0.84, "coin": 8, "stattrak": false, "souvenir": false}, {"exterior": "Souvenir Factory New", "price": 0.21, "coin": 2, "stattrak": false, "souvenir": true}, {"exterior": "Souvenir Minimal Wear", "price": 0.03, "coin": 1, "stattrak": false, "souvenir": true}, {"exterior": "Souvenir Field-Tested", "price": 0.02, "coin": 1, "stattrak": false, "souvenir": true}, {"exterior": "Souvenir Well-Worn", "price": 0.02, "coin": 1, "stattrak": false, "souvenir": true}, {"exterior": "Souvenir Battle-Scarred", "price": 0.03, "coin": 1, "stattrak": false, "souvenir": true}]}, {"name": "XM1014", "family_name": "Charter", "thumbnail": "https://steamcdn-a.akamaihd.net/apps/730/icons/econ/default_generated/weapon_xm1014_am_authority_brown_light_large.37101767e4d0abbd0248f9ee6d6b73d8c2f0dbd6.png", "rarity": "consumer", "type": "weapon", "exteriors": [{"exterior": "Factory New", "price": 1.04, "coin": 10, "stattrak": false, "souvenir": false}, {"exterior": "Minimal Wear", "price": 0.93, "coin": 9, "stattrak": false, "souvenir": false}, {"exterior": "Field-Tested", "price": 0.92, "coin": 9, "stattrak": false, "souvenir": false}, {"exterior": "Well-Worn", "price": 99.73, "coin": 997, "stattrak": false, "souvenir": false}, {"exterior": "Battle-Scarred", "price": 0.88, "coin": 8, "stattrak": false, "souvenir": false}]}, {"name": "XM1014", "family_name": "Blue Spruce", "thumbnail": "https://steamcdn-a.akamaihd.net/apps/730/icons/econ/default_generated/weapon_xm1014_so_moss_light_large.5308796fa6ef2edaa45a6c6e73c59452fc265781.png", "rarity": "consumer", "type": "weapon", "exteriors": [{"exterior": "Factory New", "price": 0.21, "coin": 2, "stattrak": false, "souvenir": false}, {"exterior": "Minimal Wear", "price": 0.01, "coin": 1, "stattrak": false, "souvenir": false}, {"exterior": "Field-Tested", "price": 0.01, "coin": 1, "stattrak": false, "souvenir": false}, {"exterior": "Well-Worn", "price": 0.15, "coin": 1, "stattrak": false, "souvenir": false}, {"exterior": "Battle-Scarred", "price": 0.01, "coin": 1, "stattrak": false, "souvenir": false}, {"exterior": "Souvenir Factory New", "price": 0.0, "coin": 1, "stattrak": false, "souvenir": true}, {"exterior": "Souvenir Minimal Wear", "price": 69.5, "coin": 695, "stattrak": false, "souvenir": true}, {"exterior": "Souvenir Field-Tested", "price": 299.18, "coin": 2991, "stattrak": false, "souvenir": true}, {"exterior": "Souvenir Well-Worn", "price": 20.04, "coin": 200, "stattrak": false, "souvenir": true}, {"exterior": "Souvenir Battle-Scarred", "price": 12.93, "coin": 129, "stattrak": false, "souvenir": true}]}, {"name": "XM1014", "family_name": "Jungle", "thumbnail": "https://steamcdn-a.akamaihd.net/apps/730/icons/econ/default_generated/weapon_xm1014_so_jungle_bravo_light_large.0b0998c1c247ffc870bbdbc4c53696cd8a974f30.png", "rarity": "consumer", "type": "weapon", "exteriors": [{"exterior": "Factory New", "price": 83.42, "coin": 834, "stattrak": false, "souvenir": false}, {"exterior": "Minimal Wear", "price": 6.45, "coin": 64, "stattrak": false, "souvenir": false}, {"exterior": "Field-Tested", "price": 2.98, "coin": 29, "stattrak": false, "souvenir": false}, {"exterior": "Well-Worn", "price": 4.28, "coin": 42, "stattrak": false, "souvenir": false}, {"exterior": "Battle-Scarred", "price": 2.3, "coin": 23, "stattrak": false, "souvenir": false}]}, {"name": "XM1014", "family_name": "Grassland", "thumbnail": "https://steamcdn-a.akamaihd.net/apps/730/icons/econ/default_generated/weapon_xm1014_so_grassland_light_large.412e08f5f190db15e6118e19c6ea0752bbaed180.png", "rarity": "consumer", "type": "weapon", "exteriors": [{"exterior": "Factory New", "price": 28.98, "coin": 289, "stattrak": false, "souvenir": false}, {"exterior": "Minimal Wear", "price": 3.74, "coin": 37, "stattrak": false, "souvenir": false}, {"exterior": "Field-Tested", "price": 2.29, "coin": 22, "stattrak": false, "souvenir": false}, {"exterior": "Well-Worn", "price": 3.43, "coin": 34, "stattrak": false, "souvenir": false}, {"exterior": "Battle-Scarred", "price": 2.54, "coin": 25, "stattrak": false, "souvenir": false}]}, {"name": "XM1014", "family_name": "Urban Perforated", "thumbnail": "https://steamcdn-a.akamaihd.net/apps/730/icons/econ/default_generated/weapon_xm1014_sp_tape_dots_urban_light_large.751c1e2059e1b9b8ef64b4cd94b22e35cccd0477.png", "rarity": "consumer", "type": "weapon", "exteriors": [{"exterior": "Factory New", "price": 14.95, "coin": 149, "stattrak": false, "souvenir": false}, {"exterior": "Minimal Wear", "price": 3.05, "coin": 30, "stattrak": false, "souvenir": false}, {"exterior": "Field-Tested", "price": 2.43, "coin": 24, "stattrak": false, "souvenir": false}, {"exterior": "Well-Worn", "price": 2.35, "coin": 23, "stattrak": false, "souvenir": false}, {"exterior": "Battle-Scarred", "price": 2.14, "coin": 21, "stattrak": false, "souvenir": false}, {"exterior": "Souvenir Factory New", "price": 4.6, "coin": 46, "stattrak": false, "souvenir": true}, {"exterior": "Souvenir Minimal Wear", "price": 0.36, "coin": 3, "stattrak": false, "souvenir": true}, {"exterior": "Souvenir Field-Tested", "price": 0.01, "coin": 1, "stattrak": false, "souvenir": true}, {"exterior": "Souvenir Well-Worn", "price": 0.31, "coin": 3, "stattrak": false, "souvenir": true}, {"exterior": "Souvenir Battle-Scarred", "price": 0.03, "coin": 1, "stattrak": false, "souvenir": true}]}]